pyviz3d/__init__.py
pyviz3d/arrow.py
pyviz3d/camera.py
pyviz3d/circles_2d.py
pyviz3d/cuboid.py
pyviz3d/labels.py
pyviz3d/lines.py
pyviz3d/mesh.py
pyviz3d/points.py
pyviz3d/polyline.py
pyviz3d/visualizer.py
pyviz3d/src/blender_tools.py
pyviz3d/src/favicon.ico
pyviz3d/src/index.html
pyviz3d/src/css/bootstrap.min.css
pyviz3d/src/js/bootstrap.min.js
pyviz3d/src/js/jquery.min.js
pyviz3d/src/js/scene.js
pyviz3d_noopen3d-0.3.4.2.dist-info/LICENSE
pyviz3d_noopen3d-0.3.4.2.dist-info/METADATA
pyviz3d_noopen3d-0.3.4.2.dist-info/WHEEL
pyviz3d_noopen3d-0.3.4.2.dist-info/top_level.txt
pyviz3d_noopen3d-0.3.4.2.dist-info/RECORD
