Metadata-Version: 2.1
Name: pyviz3d-noopen3d
Version: 0.3.4.2
Summary: PyViz3D is a python package to visualize 3D scenes.
Author-email: Francis Engelmann <francis.engelmann@gmail.com>
License: MIT License
Project-URL: Homepage, https://github.com/Silvanosky/PyViz3D
Keywords: 3d,visualizer,blender
Classifier: License :: OSI Approved :: MIT License
Classifier: Programming Language :: Python
Classifier: Programming Language :: Python :: 3
Requires-Python: >=3.8
License-File: LICENSE
Requires-Dist: numpy
